MANIFEST.in
README
setup.py
debug/__init__.py
debug/urls.py
debug/utils.py
debug/views.py
debug/templates/debug/orm_debug.html
debug/templatetags/__init__.py
debug/templatetags/orm_debug.py
django_debug.egg-info/PKG-INFO
django_debug.egg-info/SOURCES.txt
django_debug.egg-info/dependency_links.txt
django_debug.egg-info/top_level.txt